rendertron/decorators/__init__.py
rendertron/decorators/django.py
rendertron/middleware/__init__.py
rendertron/middleware/base.py
rendertron/middleware/django.py
rendertron/storage/__init__.py
rendertron/storage/base.py
rendertron/storage/django.py
rendertron/storage/dummy.py
rendertron-0.2.1.dist-info/LICENSE
rendertron-0.2.1.dist-info/METADATA
rendertron-0.2.1.dist-info/WHEEL
rendertron-0.2.1.dist-info/top_level.txt
rendertron-0.2.1.dist-info/RECORD
