Metadata-Version: 2.1
Name: rendertron
Version: 0.2.1
Summary: Rendertron middleware for python applications
Home-page: https://github.com/frontendr/python-rendertron
Author: Johan Arensman
Author-email: johan@frontendr.com
License: MIT
Keywords: rendertron render chrome django middleware
Platform: UNKNOWN
Classifier: Development Status :: 4 - Beta
Classifier: Framework :: Django
Classifier: Framework :: Django :: 2.1
Classifier: Framework :: Django :: 3.0
Classifier: Intended Audience :: Developers
Classifier: Programming Language :: Python :: 3
Classifier: License :: OSI Approved :: MIT License
Classifier: Operating System :: OS Independent
Requires-Python: >=3
